{
"name": "carrying capacity",
"lesson": 1,
"assigned_to": "nuala",
"complete": true,
"locked": "",
"media": [],
"vettings": [],
"vetted_by": [],
"comments": [],
"created_at": "2015-03-25T19:08:00.000Z"
}
{
"name": "clumped dispersion",
"lesson": 1,
"assigned_to": "jeremy",
"complete": true,
"locked": "",
"media": [],
"vettings": [],
"vetted_by": [],
"comments": [],
"created_at": "2015-03-25T19:08:00.000Z"
}
{
"name": "cohort",
"lesson": 1,
"assigned_to": "hannah",
"complete": true,
"locked": "",
"media": [],
"vettings": [],
"vetted_by": [],
"comments": [],
"created_at": "2015-03-25T19:08:00.000Z"
}
{
"name": "competition",
"lesson": 1,
"assigned_to": "amanda",
"complete": true,
"locked": "",
"media": [],
"vettings": [],
"vetted_by": [],
"comments": [],
"created_at": "2015-03-25T19:08:00.000Z"
}
{
"name": "complete count",
"lesson": 1,
"assigned_to": "riga",
"complete": true,
"locked": "",
"media": [],
"vettings": [],
"vetted_by": [],
"comments": [],
"created_at": "2015-03-25T19:08:00.000Z"
}
{
"name": "declining stage",
"lesson": 1,
"assigned_to": "andy",
"complete": true,
"locked": "",
"media": [],
"vettings": [],
"vetted_by": [],
"comments": [],
"created_at": "2015-03-25T19:08:00.000Z"
}
{
"name": "demographic transition",
"lesson": 1,
"assigned_to": "sharon",
"complete": true,
"locked": "",
"media": [],
"vettings": [],
"vetted_by": [],
"comments": [],
"created_at": "2015-03-25T19:08:00.000Z"
}
{
"name": "demography",
"lesson": 1,
"assigned_to": "daniel",
"complete": true,
"locked": "",
"media": [],
"vettings": [],
"vetted_by": [],
"comments": [],
"created_at": "2015-03-25T19:08:00.000Z"
}
{
"name": "density dependent factor",
"lesson": 1,
"assigned_to": "kevin",
"complete": true,
"locked": "",
"media": [],
"vettings": [],
"vetted_by": [],
"comments": [],
"created_at": "2015-03-25T19:08:00.000Z"
}
{
"name": "density dependent growth",
"lesson": 1,
"assigned_to": "jacob",
"complete": true,
"locked": "",
"media": [],
"vettings": [],
"vetted_by": [],
"comments": [],
"created_at": "2015-03-25T19:08:00.000Z"
}
{
"name": "density independent growth",
"lesson": 1,
"assigned_to": "richard",
"complete": true,
"locked": "",
"media": [],
"vettings": [],
"vetted_by": [],
"comments": [],
"created_at": "2015-03-25T19:08:00.000Z"
}
{
"name": "disease",
"lesson": 1,
"assigned_to": "seby",
"complete": true,
"locked": "",
"media": [],
"vettings": [],
"vetted_by": [],
"comments": [],
"created_at": "2015-03-25T19:08:00.000Z"
}
{
"name": "dispersion pattern",
"lesson": 1,
"assigned_to": "serena",
"complete": true,
"locked": "",
"media": [],
"vettings": [],
"vetted_by": [],
"comments": [],
"created_at": "2015-03-25T19:08:00.000Z"
}
{
"name": "early expanding",
"lesson": 1,
"assigned_to": "martyn",
"complete": true,
"locked": "",
"media": [],
"vettings": [],
"vetted_by": [],
"comments": [],
"created_at": "2015-03-25T19:08:00.000Z"
}
{
"name": "environment",
"lesson": 1,
"assigned_to": "ashley",
"complete": true,
"locked": "",
"media": [],
"vettings": [],
"vetted_by": [],
"comments": [],
"created_at": "2015-03-25T19:08:00.000Z"
}
{
"name": "exponential growth model",
"lesson": 1,
"assigned_to": "nuala",
"complete": true,
"locked": "",
"media": [],
"vettings": [],
"vetted_by": [],
"comments": [],
"created_at": "2015-03-25T19:08:00.000Z"
}
{
"name": "global carrying capacity",
"lesson": 1,
"assigned_to": "jeremy",
"complete": true,
"locked": "",
"media": [],
"vettings": [],
"vetted_by": [],
"comments": [],
"created_at": "2015-03-25T19:08:00.000Z"
}
{
"name": "high stationary",
"lesson": 1,
"assigned_to": "hannah",
"complete": true,
"locked": "",
"media": [],
"vettings": [],
"vetted_by": [],
"comments": [],
"created_at": "2015-03-25T19:08:00.000Z"
}
{
"name": "incomplete count",
"lesson": 1,
"assigned_to": "amanda",
"complete": true,
"locked": "",
"media": [],
"vettings": [],
"vetted_by": [],
"comments": [],
"created_at": "2015-03-25T19:08:00.000Z"
}
{
"name": "indirect count",
"lesson": 1,
"assigned_to": "riga",
"complete": true,
"locked": "",
"media": [],
"vettings": [],
"vetted_by": [],
"comments": [],
"created_at": "2015-03-25T19:08:00.000Z"
}
{
"name": "individuals",
"lesson": 1,
"assigned_to": "andy",
"complete": true,
"locked": "",
"media": [],
"vettings": [],
"vetted_by": [],
"comments": [],
"created_at": "2015-03-25T19:08:00.000Z"
}
{
"name": "intrinsic rate of increase",
"lesson": 1,
"assigned_to": "sharon",
"complete": true,
"locked": "",
"media": [],
"vettings": [],
"vetted_by": [],
"comments": [],
"created_at": "2015-03-25T19:08:00.000Z"
}
{
"name": "iteroparity",
"lesson": 1,
"assigned_to": "daniel",
"complete": true,
"locked": "",
"media": [],
"vettings": [],
"vetted_by": [],
"comments": [],
"created_at": "2015-03-25T19:08:00.000Z"
}
{
"name": "K-selection",
"lesson": 1,
"assigned_to": "kevin",
"complete": true,
"locked": "",
"media": [],
"vettings": [],
"vetted_by": [],
"comments": [],
"created_at": "2015-03-25T19:08:00.000Z"
}
{
"name": "late expanding",
"lesson": 1,
"assigned_to": "jacob",
"complete": true,
"locked": "",
"media": [],
"vettings": [],
"vetted_by": [],
"comments": [],
"created_at": "2015-03-25T19:08:00.000Z"
}
{
"name": "life table",
"lesson": 1,
"assigned_to": "richard",
"complete": true,
"locked": "",
"media": [],
"vettings": [],
"vetted_by": [],
"comments": [],
"created_at": "2015-03-25T19:08:00.000Z"
}
{
"name": "logistic growth model",
"lesson": 1,
"assigned_to": "seby",
"complete": true,
"locked": "",
"media": [],
"vettings": [],
"vetted_by": [],
"comments": [],
"created_at": "2015-03-25T19:08:00.000Z"
}
{
"name": "low stationary",
"lesson": 1,
"assigned_to": "serena",
"complete": true,
"locked": "",
"media": [],
"vettings": [],
"vetted_by": [],
"comments": [],
"created_at": "2015-03-25T19:08:00.000Z"
}
{
"name": "mark recapture method",
"lesson": 1,
"assigned_to": "martyn",
"complete": true,
"locked": "",
"media": [],
"vettings": [],
"vetted_by": [],
"comments": [],
"created_at": "2015-03-25T19:08:00.000Z"
}
{
"name": "per capita birth rate",
"lesson": 1,
"assigned_to": "ashley",
"complete": true,
"locked": "",
"media": [],
"vettings": [],
"vetted_by": [],
"comments": [],
"created_at": "2015-03-25T19:08:00.000Z"
}
{
"name": "per capita death rate",
"lesson": 1,
"assigned_to": "nuala",
"complete": true,
"locked": "",
"media": [],
"vettings": [],
"vetted_by": [],
"comments": [],
"created_at": "2015-03-25T19:08:00.000Z"
}
{
"name": "population",
"lesson": 1,
"assigned_to": "jeremy",
"complete": true,
"locked": "",
"media": [],
"vettings": [],
"vetted_by": [],
"comments": [],
"created_at": "2015-03-25T19:08:00.000Z"
}
{
"name": "population density",
"lesson": 1,
"assigned_to": "hannah",
"complete": true,
"locked": "",
"media": [],
"vettings": [],
"vetted_by": [],
"comments": [],
"created_at": "2015-03-25T19:08:00.000Z"
}
{
"name": "population growth",
"lesson": 1,
"assigned_to": "amanda",
"complete": true,
"locked": "",
"media": [],
"vettings": [],
"vetted_by": [],
"comments": [],
"created_at": "2015-03-25T19:08:00.000Z"
}
{
"name": "population sampling technique",
"lesson": 1,
"assigned_to": "riga",
"complete": true,
"locked": "",
"media": [],
"vettings": [],
"vetted_by": [],
"comments": [],
"created_at": "2015-03-25T19:08:00.000Z"
}
{
"name": "predation",
"lesson": 1,
"assigned_to": "andy",
"complete": true,
"locked": "",
"media": [],
"vettings": [],
"vetted_by": [],
"comments": [],
"created_at": "2015-03-25T19:08:00.000Z"
}
{
"name": "r-selection",
"lesson": 1,
"assigned_to": "sharon",
"complete": true,
"locked": "",
"media": [],
"vettings": [],
"vetted_by": [],
"comments": [],
"created_at": "2015-03-25T19:08:00.000Z"
}
{
"name": "random dispersion",
"lesson": 1,
"assigned_to": "daniel",
"complete": true,
"locked": "",
"media": [],
"vettings": [],
"vetted_by": [],
"comments": [],
"created_at": "2015-03-25T19:08:00.000Z"
}
{
"name": "reproductive rate",
"lesson": 1,
"assigned_to": "kevin",
"complete": true,
"locked": "",
"media": [],
"vettings": [],
"vetted_by": [],
"comments": [],
"created_at": "2015-03-25T19:08:00.000Z"
}
{
"name": "reproductive strategy",
"lesson": 1,
"assigned_to": "jacob",
"complete": true,
"locked": "",
"media": [],
"vettings": [],
"vetted_by": [],
"comments": [],
"created_at": "2015-03-25T19:08:00.000Z"
}
{
"name": "reproductive table",
"lesson": 1,
"assigned_to": "richard",
"complete": true,
"locked": "",
"media": [],
"vettings": [],
"vetted_by": [],
"comments": [],
"created_at": "2015-03-25T19:08:00.000Z"
}
{
"name": "semelparity",
"lesson": 1,
"assigned_to": "seby",
"complete": true,
"locked": "",
"media": [],
"vettings": [],
"vetted_by": [],
"comments": [],
"created_at": "2015-03-25T19:08:00.000Z"
}
{
"name": "survivorship curve",
"lesson": 1,
"assigned_to": "serena",
"complete": true,
"locked": "",
"media": [],
"vettings": [],
"vetted_by": [],
"comments": [],
"created_at": "2015-03-25T19:08:00.000Z"
}
{
"name": "territoriality",
"lesson": 1,
"assigned_to": "martyn",
"complete": true,
"locked": "",
"media": [],
"vettings": [],
"vetted_by": [],
"comments": [],
"created_at": "2015-03-25T19:08:00.000Z"
}
{
"name": "toxic waste",
"lesson": 1,
"assigned_to": "ashley",
"complete": true,
"locked": "",
"media": [],
"vettings": [],
"vetted_by": [],
"comments": [],
"created_at": "2015-03-25T19:08:00.000Z"
}
{
"name": "uniform (spaced) dispersion",
"lesson": 1,
"assigned_to": "nuala",
"complete": true,
"locked": "",
"media": [],
"vettings": [],
"vetted_by": [],
"comments": [],
"created_at": "2015-03-25T19:08:00.000Z"
}
{
"name": "zero population growth",
"lesson": 1,
"assigned_to": "jeremy",
"complete": true,
"locked": "",
"media": [],
"vettings": [],
"vetted_by": [],
"comments": [],
"created_at": "2015-03-25T19:08:00.000Z"
}
